pydragonfly/__init__.py
pydragonfly/version.py
pydragonfly/cli/__init__.py
pydragonfly/cli/_utils.py
pydragonfly/cli/config.py
pydragonfly/cli/resources/__init__.py
pydragonfly/cli/resources/_renderables.py
pydragonfly/cli/resources/analysis.py
pydragonfly/cli/resources/profile.py
pydragonfly/cli/resources/rule.py
pydragonfly/cli/resources/user_access_info.py
pydragonfly/sdk/__init__.py
pydragonfly/sdk/const.py
pydragonfly/sdk/dragonfly.py
pydragonfly/sdk/exceptions.py
pydragonfly/sdk/resources/__init__.py
pydragonfly/sdk/resources/_utils.py
pydragonfly/sdk/resources/action.py
pydragonfly/sdk/resources/analysis.py
pydragonfly/sdk/resources/invitation.py
pydragonfly/sdk/resources/organization.py
pydragonfly/sdk/resources/profile.py
pydragonfly/sdk/resources/report.py
pydragonfly/sdk/resources/rule.py
pydragonfly/sdk/resources/sample.py
pydragonfly/sdk/resources/session.py
pydragonfly/sdk/resources/user_access_info.py
pydragonfly/sdk/resources/user_preferences.py
tests/__init__.py
tests/mock_utils.py
tests/test_dragonfly.py
tests/cli/__init__.py
tests/cli/test_basic.py
tests/cli/test_config.py
tests/resources/__init__.py
tests/resources/test_action.py
tests/resources/test_analysis.py
tests/resources/test_invitation.py
tests/resources/test_organization.py
tests/resources/test_profile.py
tests/resources/test_report.py
tests/resources/test_rule.py
tests/resources/test_sample.py
tests/resources/test_session.py
tests/resources/test_user_access_info.py
tests/resources/test_user_preferences.py
pydragonfly-0.1.2.dist-info/LICENSE
pydragonfly-0.1.2.dist-info/METADATA
pydragonfly-0.1.2.dist-info/WHEEL
pydragonfly-0.1.2.dist-info/entry_points.txt
pydragonfly-0.1.2.dist-info/top_level.txt
pydragonfly-0.1.2.dist-info/RECORD
