Metadata-Version: 2.1
Name: pydragonfly
Version: 0.1.2
Summary: Robust Python SDK and CLI for Certego's Dragonfly service's API
Home-page: https://github.com/certego/pydragonfly
Author: Certego S.R.L
License: UNKNOWN
Project-URL: Documentation, https://github.com/certego/pydragonfly
Project-URL: Source, https://github.com/certego/pydragonfly
Project-URL: Tracker, https://github.com/certego/pydragonfly/issues
Keywords: certego dragonfly sdk python command line osint threat intel malware
Platform: UNKNOWN
Classifier: Development Status :: 3 - Alpha
Classifier: Intended Audience :: Developers
Classifier: License :: OSI Approved :: BSD License
Classifier: Programming Language :: Python :: 3.6
Classifier: Programming Language :: Python :: 3.7
Classifier: Programming Language :: Python :: 3.8
Classifier: Programming Language :: Python :: 3.9
Classifier: Programming Language :: Python :: 3.10
Classifier: Topic :: Software Development :: Libraries :: Python Modules
Requires-Python: >=3.6
License-File: LICENSE
Requires-Dist: django-rest-client[cli] (==0.0.1)
Requires-Dist: typing-extensions
Requires-Dist: click (>=7.0)
Requires-Dist: rich (~=11.1.0)
Requires-Dist: click-creds (~=0.0.3)
Requires-Dist: dataclasses ; python_version < "3.7"
Provides-Extra: dev
Requires-Dist: black (==20.8b1) ; extra == 'dev'
Requires-Dist: flake8 (==3.9.1) ; extra == 'dev'
Requires-Dist: pre-commit (==2.12.1) ; extra == 'dev'
Requires-Dist: tox (==3.23.0) ; extra == 'dev'
Requires-Dist: tox-gh-actions (==2.5.0) ; extra == 'dev'
Requires-Dist: codecov ; extra == 'dev'
Requires-Dist: coverage ; extra == 'dev'
Requires-Dist: django-rest-client[cli] (==0.0.1) ; extra == 'dev'
Requires-Dist: typing-extensions ; extra == 'dev'
Requires-Dist: click (>=7.0) ; extra == 'dev'
Requires-Dist: rich (~=11.1.0) ; extra == 'dev'
Requires-Dist: click-creds (~=0.0.3) ; extra == 'dev'
Requires-Dist: dataclasses ; (python_version < "3.7") and extra == 'dev'
Provides-Extra: test
Requires-Dist: black (==20.8b1) ; extra == 'test'
Requires-Dist: flake8 (==3.9.1) ; extra == 'test'
Requires-Dist: pre-commit (==2.12.1) ; extra == 'test'
Requires-Dist: tox (==3.23.0) ; extra == 'test'
Requires-Dist: tox-gh-actions (==2.5.0) ; extra == 'test'
Requires-Dist: codecov ; extra == 'test'
Requires-Dist: coverage ; extra == 'test'
Requires-Dist: django-rest-client[cli] (==0.0.1) ; extra == 'test'
Requires-Dist: typing-extensions ; extra == 'test'
Requires-Dist: click (>=7.0) ; extra == 'test'
Requires-Dist: rich (~=11.1.0) ; extra == 'test'
Requires-Dist: click-creds (~=0.0.3) ; extra == 'test'
Requires-Dist: dataclasses ; (python_version < "3.7") and extra == 'test'
